funchouse/__init__.py
funchouse/repository.py
funchouse/pipelines/__init__.py
funchouse/pipelines/my_pipeline.py
funchouse/schedules/__init__.py
funchouse/schedules/my_hourly_schedule.py
funchouse/sensors/__init__.py
funchouse/sensors/my_sensor.py
funchouse/solids/__init__.py
funchouse/solids/hello.py
funchouse_tests/test_pipelines/__init__.py
funchouse_tests/test_pipelines/test_my_pipeline.py
funchouse_tests/test_solids/__init__.py
funchouse_tests/test_solids/test_hello.py
funchouse-0.0.0.dist-info/METADATA
funchouse-0.0.0.dist-info/WHEEL
funchouse-0.0.0.dist-info/top_level.txt
funchouse-0.0.0.dist-info/RECORD
